coordinates/__init__.py
coordinates/classes.py
coordinates/version.py
coordinates-0.4.0.dist-info/LICENSE
coordinates-0.4.0.dist-info/METADATA
coordinates-0.4.0.dist-info/WHEEL
coordinates-0.4.0.dist-info/top_level.txt
coordinates-0.4.0.dist-info/RECORD
