Metadata-Version: 2.1
Name: coordinates
Version: 0.4.0
Summary: Convenience class for doing maths with explicit coordinates
Home-page: https://github.com/clbarnes/coordinates
Author: Chris L Barnes
Author-email: barnesc@janelia.hhmi.org
License: MIT
Keywords: coordinate spatial mathdict
Platform: UNKNOWN
Classifier: Development Status :: 4 - Beta
Classifier: License :: OSI Approved :: MIT License
Classifier: Programming Language :: Python
Classifier: Programming Language :: Python :: 3.8
Classifier: Programming Language :: Python :: 3.7
Classifier: Programming Language :: Python :: 3.6
Requires-Python: >=3.6
